[
  {
    "date": "2025 / 11 / 25",
    "category": "Media Releases",
    "brand": "Volkswagen Taiwan",
    "title": "熱血狂放靈魂 Volkswagen The new Polo GTI 席捲全台",
    "excerpt": "Volkswagen 本月推出 The new Polo GTI 獲熱切矚目，首批 50 輛甫上市即銷售一空，台灣福斯汽車極力向德國原廠爭取追加生產，期待更多車迷能同享正統小鋼砲無與倫比的純粹駕馭樂趣。",
    "url": "https://www.volkswagen.com.tw/zh/about-volkswagen/news/2025-11-25.html",
    "image": "images/new1.jpg"
  },
  {
    "date": "2025 / 11 / 20",
    "category": "Media Releases",
    "brand": "Audi Taiwan",
    "title": "台灣奧迪榮獲 2025 年「臺灣客服中心評鑑」金獎殊榮 引領汽車賣場業 豎立品牌服務標竿",
    "excerpt": "台灣奧迪再創佳績！在 2025 年臺灣客服中心評鑑中，憑藉卓越的客戶服務品質，自全台 146 家受評企業中脫穎而出，榮獲汽車賣場業金獎肯定。該獎項由臺灣服務稽核協會 (TSAA) 主辦、工商時報協辦，今年已邁入第四屆。",
    "url": "https://www.audi.com.tw/zh/news-center/news-2025-07-12/1120-audi-service-awards/",
    "image": "images/news2.jpg"
  },
  {
    "date": "2025 / 10 / 20",
    "category": "Events",
    "brand": "Volkswagen Group Taiwan",
    "title": "新篇章啟動 — 歡迎來到 Volkswagen Group Taiwan 的新家",
    "excerpt": "Volkswagen Group Taiwan 的全新辦公室正式落腳在充滿創意與活力的台北南港。匯聚科技、設計與合作的能量，象徵著我們邁向未來的重要一步。",
    "url": "https://www.linkedin.com/posts/volkswagen-group-taiwan_volkswagengrouptaiwan-vgt-audi-activity-7391384313004679169-5MJm?utm_source=share&utm_medium=member_desktop&rcm=ACoAAC5uvpkB8Oqv7V7GG-6Gw87TMSwwQuzngvQ",
    "image": "images/news3.jpg"
  }
]
